test_step/__init__.py
test_step/logging.py
test_step/util.py
test_step/html_reporting/__init__.py
test_step/html_reporting/extras.py
test_step/html_reporting/plugin.py
test_step/steps/__init__.py
test_step/steps/plugin.py
test_step/steps/step.py
test_step-1.0.0.dist-info/licenses/LICENSE.md
test_step-1.0.0.dist-info/METADATA
test_step-1.0.0.dist-info/WHEEL
test_step-1.0.0.dist-info/entry_points.txt
test_step-1.0.0.dist-info/top_level.txt
test_step-1.0.0.dist-info/RECORD
