Metadata-Version: 2.4
Name: test-step
Version: 1.0.0
Summary: Test step decorator and HTML reporting plugin for pytest
Home-page: https://github.com/cujoai/test-step
Author: CUJO AI TestOps
Author-email: testops@cujo.com
Classifier: Programming Language :: Python :: 3
Classifier: Operating System :: OS Independent
Classifier: Framework :: Pytest
Requires-Python: >=3.10
License-File: LICENSE.md
Requires-Dist: pytest<10,>=8
Requires-Dist: pytest-xdist~=3.8
Requires-Dist: pytest-html~=4.1
Provides-Extra: test
Requires-Dist: junitparser~=4.0; extra == "test"
Requires-Dist: ruff==0.12; extra == "test"
Dynamic: author
Dynamic: author-email
Dynamic: classifier
Dynamic: description
Dynamic: description-content-type
Dynamic: home-page
Dynamic: license-file
Dynamic: provides-extra
Dynamic: requires-dist
Dynamic: requires-python
Dynamic: summary
